<?xml version="1.0"?>
<!--<!DOCTYPE metadata SYSTEM "http://www.esri.com/metadata/esriprof80.dtd">-->
<metadata xml:lang="es"><Esri><CreaDate>20120726</CreaDate><CreaTime>12140500</CreaTime><SyncOnce>TRUE</SyncOnce><DataProperties><lineage><Process Name="Add Field (5)" ToolSource="C:\Archivos de programa\ArcGIS\ArcToolbox\Toolboxes\Data Management Tools.tbx\AddField" Date="20100907" Time="184015">AddField VINCULACION.FC_882_Manzanas CLAVE_OLD TEXT # # 15 # NULLABLE NON_REQUIRED # VINCULACION.FC_882_Manzanas</Process><Process Name="Add Field (5)" ToolSource="C:\Archivos de programa\ArcGIS\ArcToolbox\Toolboxes\Data Management Tools.tbx\AddField" Date="20100907" Time="184103">AddField VINCULACION.FC_882_Manzanas CLAVE_OLD TEXT # # 15 # NULLABLE NON_REQUIRED # VINCULACION.FC_882_Manzanas</Process><Process Name="Add Field (5)" ToolSource="C:\Archivos de programa\ArcGIS\ArcToolbox\Toolboxes\Data Management Tools.tbx\AddField" Date="20100907" Time="184652">AddField VINCULACION.FC_882_Manzanas CLAVE_OLD TEXT # # 15 # NULLABLE NON_REQUIRED # VINCULACION.FC_882_Manzanas</Process><Process Name="Add Field (5)" ToolSource="C:\Archivos de programa\ArcGIS\ArcToolbox\Toolboxes\Data Management Tools.tbx\AddField" Date="20100908" Time="085036">AddField VINCULACION.FC_882_Manzanas CLAVE_OLD TEXT # # 15 # NULLABLE NON_REQUIRED # VINCULACION.FC_882_Manzanas</Process><Process Name="Add Field (6)" ToolSource="C:\Archivos de programa\ArcGIS\ArcToolbox\Toolboxes\Data Management Tools.tbx\AddField" Date="20100908" Time="085037">AddField VINCULACION.FC_882_Manzanas TOT_VIV_2001 SHORT # # 15 # NULLABLE NON_REQUIRED # VINCULACION.FC_882_Manzanas</Process><Process Name="Remove Join" ToolSource="C:\Archivos de programa\ArcGIS\ArcToolbox\Toolboxes\Data Management Tools.tbx\RemoveJoin" Date="20100908" Time="091114">RemoveJoin VINCULACION.FC_882_Manzanas outputtable VINCULACION.FC_882_Manzanas</Process><Process Name="Calculate Field" ToolSource="C:\Archivos de programa\ArcGIS\ArcToolbox\Toolboxes\Data Management Tools.tbx\CalculateField" Date="20100908" Time="091242">CalculateField VINCULACION.FC_882_Manzanas TOT_VIV_2001 [TOT_VIV] VB # VINCULACION.FC_882_Manzanas</Process><Process Name="Calculate Field (3)" ToolSource="C:\Archivos de programa\ArcGIS\ArcToolbox\Toolboxes\Data Management Tools.tbx\CalculateField" Date="20100908" Time="091243">CalculateField VINCULACION.FC_882_Manzanas CLAVE_OLD [CLAVE] VB # VINCULACION.FC_882_Manzanas</Process><Process Name="Calculate Field (4)" ToolSource="C:\Archivos de programa\ArcGIS\ArcToolbox\Toolboxes\Data Management Tools.tbx\CalculateField" Date="20100908" Time="091243">CalculateField VINCULACION.FC_882_Manzanas TOT_VIV 0 VB # VINCULACION.FC_882_Manzanas</Process><Process Name="Calculate Field" ToolSource="C:\Archivos de programa\ArcGIS\ArcToolbox\Toolboxes\Data Management Tools.tbx\CalculateField" Date="20100908" Time="091348">CalculateField VINCULACION.FC_882_Manzanas TOT_VIV_2001 [TOT_VIV] VB # VINCULACION.FC_882_Manzanas</Process><Process Name="Calculate Field (3)" ToolSource="C:\Archivos de programa\ArcGIS\ArcToolbox\Toolboxes\Data Management Tools.tbx\CalculateField" Date="20100908" Time="091348">CalculateField VINCULACION.FC_882_Manzanas CLAVE_OLD [CLAVE] VB # VINCULACION.FC_882_Manzanas</Process><Process Name="Calculate Field (4)" ToolSource="C:\Archivos de programa\ArcGIS\ArcToolbox\Toolboxes\Data Management Tools.tbx\CalculateField" Date="20100908" Time="091348">CalculateField VINCULACION.FC_882_Manzanas TOT_VIV 0 VB # VINCULACION.FC_882_Manzanas</Process><Process Name="Add Field (5)" ToolSource="C:\Archivos de programa\ArcGIS\ArcToolbox\Toolboxes\Data Management Tools.tbx\AddField" Date="20100908" Time="091434">AddField VINCULACION.FC_882_Manzanas CLAVE_OLD TEXT # # 15 # NULLABLE NON_REQUIRED # VINCULACION.FC_882_Manzanas</Process><Process Name="Add Field (6)" ToolSource="C:\Archivos de programa\ArcGIS\ArcToolbox\Toolboxes\Data Management Tools.tbx\AddField" Date="20100908" Time="091434">AddField VINCULACION.FC_882_Manzanas TOT_VIV_2001 SHORT # # 15 # NULLABLE NON_REQUIRED # VINCULACION.FC_882_Manzanas</Process><Process Name="Calculate Field" ToolSource="C:\Archivos de programa\ArcGIS\ArcToolbox\Toolboxes\Data Management Tools.tbx\CalculateField" Date="20100908" Time="091453">CalculateField VINCULACION.FC_882_Manzanas TOT_VIV_2001 [TOT_VIV] VB # VINCULACION.FC_882_Manzanas</Process><Process Name="Calculate Field (3)" ToolSource="C:\Archivos de programa\ArcGIS\ArcToolbox\Toolboxes\Data Management Tools.tbx\CalculateField" Date="20100908" Time="091456">CalculateField VINCULACION.FC_882_Manzanas CLAVE_OLD [CLAVE] VB # VINCULACION.FC_882_Manzanas</Process><Process Name="Calculate Field (4)" ToolSource="C:\Archivos de programa\ArcGIS\ArcToolbox\Toolboxes\Data Management Tools.tbx\CalculateField" Date="20100908" Time="091458">CalculateField VINCULACION.FC_882_Manzanas TOT_VIV 0 VB # VINCULACION.FC_882_Manzanas</Process><Process Name="Remove Join" ToolSource="C:\Archivos de programa\ArcGIS\ArcToolbox\Toolboxes\Data Management Tools.tbx\RemoveJoin" Date="20100908" Time="091543">RemoveJoin VINCULACION.FC_882_Manzanas outputtable VINCULACION.FC_882_Manzanas</Process><Process Name="Add Field (5)" ToolSource="C:\Archivos de programa\ArcGIS\ArcToolbox\Toolboxes\Data Management Tools.tbx\AddField" Date="20100908" Time="115735">AddField VINCULACION.FC_882_Manzanas CLAVE_OLD TEXT # # 15 # NULLABLE NON_REQUIRED # VINCULACION.FC_882_Manzanas</Process><Process Name="Add Field (6)" ToolSource="C:\Archivos de programa\ArcGIS\ArcToolbox\Toolboxes\Data Management Tools.tbx\AddField" Date="20100908" Time="115735">AddField VINCULACION.FC_882_Manzanas TOT_VIV_2001 SHORT # # 15 # NULLABLE NON_REQUIRED # VINCULACION.FC_882_Manzanas</Process><Process Name="Calculate Field" ToolSource="C:\Archivos de programa\ArcGIS\ArcToolbox\Toolboxes\Data Management Tools.tbx\CalculateField" Date="20100908" Time="120020">CalculateField VINCULACION.FC_882_Manzanas TOT_VIV_2001 [TOT_VIV] VB # VINCULACION.FC_882_Manzanas</Process><Process Name="Calculate Field (3)" ToolSource="C:\Archivos de programa\ArcGIS\ArcToolbox\Toolboxes\Data Management Tools.tbx\CalculateField" Date="20100908" Time="120033">CalculateField VINCULACION.FC_882_Manzanas CLAVE_OLD [CLAVE] VB # VINCULACION.FC_882_Manzanas</Process><Process Name="Calculate Field (4)" ToolSource="C:\Archivos de programa\ArcGIS\ArcToolbox\Toolboxes\Data Management Tools.tbx\CalculateField" Date="20100908" Time="120049">CalculateField VINCULACION.FC_882_Manzanas TOT_VIV 0 VB # VINCULACION.FC_882_Manzanas</Process><Process Name="Remove Join" ToolSource="C:\Archivos de programa\ArcGIS\ArcToolbox\Toolboxes\Data Management Tools.tbx\RemoveJoin" Date="20100908" Time="120522">RemoveJoin VINCULACION.FC_882_Manzanas outputtable VINCULACION.FC_882_Manzanas</Process></lineage></DataProperties><MetaID>{F27494A7-E039-4BA5-90EF-6E79D92A6BA6}</MetaID></Esri><idinfo><citation><citeinfo><onlink Sync="TRUE"></onlink></citeinfo></citation></idinfo><distInfo><distributor><distorTran><onLineSrc><linkage Sync="TRUE">file://</linkage><protocol Sync="TRUE">Local Area Network</protocol></onLineSrc></distorTran></distributor></distInfo><dataqual><lineage><procstep><procdesc Sync="TRUE">Dataset copied.</procdesc><srcused Sync="TRUE">Server=direccion; Service=5152; User=consulta; Version=SDE.DEFAULT</srcused><procdate Sync="TRUE">20120726</procdate><proctime Sync="TRUE">12140500</proctime></procstep></lineage></dataqual></metadata>
